{
  "generatedAt": "2026-07-07T14:47:47.777Z",
  "cycleId": "2026-07-07T12:00:00.000Z",
  "links": [
    {
      "a": "dc0c797b",
      "b": "47dfc368",
      "relation": "similar_to",
      "weight": 0.07
    },
    {
      "a": "dc0c797b",
      "b": "7e8a4b0b",
      "relation": "similar_to",
      "weight": 0.11
    },
    {
      "a": "1bcc782f",
      "b": "7e8a4b0b",
      "relation": "similar_to",
      "weight": 0.05
    },
    {
      "a": "47dfc368",
      "b": "7e8a4b0b",
      "relation": "similar_to",
      "weight": 0.04
    }
  ]
}
